syscorun/__init__.py
syscorun-0.1.1b1.dist-info/WHEEL
syscorun-0.1.1b1.dist-info/entry_points.txt
syscorun-0.1.1b1.dist-info/METADATA
syscorun-0.1.1b1.dist-info/RECORD
