Metadata-Version: 2.3
Name: syscorun
Version: 0.1.1b1
Summary: Execution of system and control tools
Keywords: science,engineering,education,systems,controls,controller,discrete-time,model-based,data-driven
Author: Silvan Stadelmann
Author-email: Silvan Stadelmann <silvasta3@gmail.com>
License: Apache License 2.0
Classifier: Development Status :: 3 - Alpha
Requires-Dist: loguru>=0.7.3
Requires-Dist: rich>=14.1.0
Requires-Dist: sympy>=1.14.0
Requires-Dist: sysco
Requires-Dist: syscovis
Requires-Python: >=3.13
Project-URL: Repository, https://github.com/silvasta/syscorun
